<?xml version="1.0" encoding="UTF-8"?>
<AppiumAUT>
  <XCUIElementTypeApplication type="XCUIElementTypeApplication" name="지도" label="지도" enabled="true" visible="true" accessible="false" x="0" y="0" width="393" height="852" index="0">
    <XCUIElementTypeWindow type="XCUIElementTypeWindow" name="Maps.Application" enabled="true" visible="true" accessible="false" x="0" y="0" width="393" height="852" index="0">
      <XCUIElementTypeOther type="XCUIElementTypeOther" enabled="true" visible="true" accessible="false" x="0" y="0" width="393" height="852" index="0">
        <XCUIElementTypeOther type="XCUIElementTypeOther" enabled="true" visible="true" accessible="false" x="0" y="0" width="393" height="852" index="0">
          <XCUIElementTypeOther type="XCUIElementTypeOther" enabled="true" visible="true" accessible="false" x="-393" y="-852" width="1179" height="2556" index="0"/>
          <XCUIElementTypeOther type="XCUIElementTypeOther" enabled="true" visible="true" accessible="false" x="0" y="0" width="393" height="852" index="1">
            <XCUIElementTypeOther type="XCUIElementTypeOther" enabled="true" visible="true" accessible="false" x="0" y="0" width="393" height="852" index="0">
              <XCUIElementTypeOther type="XCUIElementTypeOther" name="나의 위치" label="나의 위치" enabled="true" visible="true" accessible="true" x="175" y="241" width="43" height="45" index="0"/>
              <XCUIElementTypeOther type="XCUIElementTypeOther" enabled="true" visible="true" accessible="false" x="0" y="0" width="393" height="852" index="1">
                <XCUIElementTypeMap type="XCUIElementTypeMap" enabled="true" visible="true" accessible="false" x="0" y="0" width="393" height="852" index="0">
                  <XCUIElementTypeOther type="XCUIElementTypeOther" name="VKPointFeature" label="광화문광장" enabled="true" visible="true" accessible="true" x="155" y="45" width="31" height="31" index="0"/>
                  <XCUIElementTypeOther type="XCUIElementTypeOther" name="VKPointFeature" label="포시즌스 호텔 서울" enabled="true" visible="true" accessible="true" x="120" y="128" width="31" height="31" index="1"/>
                  <XCUIElementTypeOther type="XCUIElementTypeOther" name="VKPointFeature" label="서울역사박물관" enabled="true" visible="true" accessible="true" x="4" y="131" width="31" height="31" index="2"/>
                  <XCUIElementTypeOther type="XCUIElementTypeOther" name="VKPointFeature" label="종각역" enabled="true" visible="true" accessible="true" x="318" y="143" width="31" height="31" index="3"/>
                  <XCUIElementTypeOther type="XCUIElementTypeOther" name="VKPointFeature" label="코리아나 호텔" enabled="true" visible="true" accessible="true" x="144" y="201" width="31" height="31" index="4"/>
                  <XCUIElementTypeOther type="XCUIElementTypeOther" name="VKPointFeature" label="뉴서울호텔" enabled="true" visible="true" accessible="true" x="184" y="206" width="31" height="31" index="5"/>
                  <XCUIElementTypeOther type="XCUIElementTypeOther" name="VKPointFeature" label="광통관" enabled="true" visible="true" accessible="true" x="301" y="213" width="31" height="31" index="6"/>
                  <XCUIElementTypeOther type="XCUIElementTypeOther" name="VKPointFeature" label="서울특별시청" enabled="true" visible="true" accessible="true" x="190" y="243" width="31" height="31" index="7"/>
                  <XCUIElementTypeOther type="XCUIElementTypeOther" name="VKPointFeature" label="을지로입구역" enabled="true" visible="true" accessible="true" x="277" y="256" width="31" height="31" index="8"/>
                  <XCUIElementTypeOther type="XCUIElementTypeOther" name="VKPointFeature" label="덕수궁" enabled="true" visible="true" accessible="true" x="106" y="269" width="31" height="31" index="9"/>
                  <XCUIElementTypeOther type="XCUIElementTypeOther" name="VKPointFeature" label="서울광장" enabled="true" visible="true" accessible="true" x="182" y="274" width="31" height="31" index="10"/>
                  <XCUIElementTypeOther type="XCUIElementTypeOther" name="VKPointFeature" label="Apple 명동" enabled="true" visible="true" accessible="true" x="293" y="301" width="31" height="31" index="11"/>
                  <XCUIElementTypeOther type="XCUIElementTypeOther" name="VKPointFeature" label="더 플라자" enabled="true" visible="true" accessible="true" x="181" y="303" width="31" height="31" index="12"/>
                  <XCUIElementTypeOther type="XCUIElementTypeOther" name="VKPointFeature" label="다이소" enabled="true" visible="true" accessible="true" x="149" y="304" width="31" height="31" index="13"/>
                  <XCUIElementTypeOther type="XCUIElementTypeOther" name="VKPointFeature" label="롯데백화점" enabled="true" visible="true" accessible="true" x="266" y="316" width="31" height="31" index="14"/>
                  <XCUIElementTypeOther type="XCUIElementTypeOther" name="VKPointFeature" label="공공개방화장실" enabled="true" visible="true" accessible="true" x="321" y="333" width="31" height="31" index="15"/>
                  <XCUIElementTypeOther type="XCUIElementTypeOther" name="VKPointFeature" label="프레이저플레이스센트럴 서울" enabled="true" visible="true" accessible="true" x="-11" y="363" width="31" height="31" index="16"/>
                  <XCUIElementTypeOther type="XCUIElementTypeOther" name="VKPointFeature" label="명동교자" enabled="true" visible="true" accessible="true" x="360" y="365" width="31" height="31" index="17"/>
                  <XCUIElementTypeOther type="XCUIElementTypeOther" name="VKPointFeature" label="호텔8아워즈" enabled="true" visible="true" accessible="true" x="181" y="378" width="31" height="31" index="18"/>
                  <XCUIElementTypeOther type="XCUIElementTypeOther" name="VKPointFeature" label="호텔 그레이스리 서울" enabled="true" visible="true" accessible="true" x="155" y="395" width="31" height="31" index="19"/>
                  <XCUIElementTypeOther type="XCUIElementTypeOther" name="VKPointFeature" label="신세계백화점" enabled="true" visible="true" accessible="true" x="251" y="414" width="31" height="31" index="20"/>
                  <XCUIElementTypeOther type="XCUIElementTypeOther" name="VKPointFeature" label="숭례문" enabled="true" visible="true" accessible="true" x="118" y="441" width="31" height="31" index="21"/>
                </XCUIElementTypeMap>
                <XCUIElementTypeOther type="XCUIElementTypeOther" name="AnnotationContainer" enabled="true" visible="false" accessible="false" x="0" y="0" width="393" height="852" index="1">
                  <XCUIElementTypeOther type="XCUIElementTypeOther" name="나의 위치" label="나의 위치" enabled="true" visible="true" accessible="true" x="175" y="241" width="43" height="45" index="0"/>
                </XCUIElementTypeOther>
              </XCUIElementTypeOther>
            </XCUIElementTypeOther>
            <XCUIElementTypeOther type="XCUIElementTypeOther" enabled="true" visible="true" accessible="false" x="0" y="0" width="393" height="59" index="1">
              <XCUIElementTypeOther type="XCUIElementTypeOther" enabled="true" visible="true" accessible="false" x="0" y="0" width="393" height="59" index="0">
                <XCUIElementTypeOther type="XCUIElementTypeOther" enabled="true" visible="true" accessible="false" x="0" y="0" width="393" height="59" index="0"/>
              </XCUIElementTypeOther>
            </XCUIElementTypeOther>
            <XCUIElementTypeOther type="XCUIElementTypeOther" name="ChromeOverlayController" enabled="true" visible="true" accessible="false" x="0" y="0" width="393" height="852" index="2">
              <XCUIElementTypeOther type="XCUIElementTypeOther" name="IOSCardsOverlay.OverlayVC" enabled="true" visible="true" accessible="false" x="0" y="0" width="393" height="852" index="0">
                <XCUIElementTypeOther type="XCUIElementTypeOther" name="IOSCardsOverlay.OverlayVC.OverlayView" enabled="true" visible="true" accessible="false" x="0" y="59" width="393" height="410" index="0"/>
              </XCUIElementTypeOther>
              <XCUIElementTypeOther type="XCUIElementTypeOther" name="IOSChromeViewController&lt;0x105821200&gt;.IOSFloatingControlsViewController&lt;0x106894000&gt;" enabled="true" visible="true" accessible="false" x="10" y="69" width="373" height="390" index="1">
                <XCUIElementTypeOther type="XCUIElementTypeOther" name="SettingsTipView" enabled="true" visible="true" accessible="false" x="20" y="69" width="319" height="63" index="0">
                  <XCUIElementTypeOther type="XCUIElementTypeOther" enabled="true" visible="true" accessible="false" x="20" y="69" width="319" height="63" index="0">
                    <XCUIElementTypeOther type="XCUIElementTypeOther" enabled="true" visible="true" accessible="false" x="10" y="59" width="339" height="83" index="0">
                      <XCUIElementTypeOther type="XCUIElementTypeOther" enabled="true" visible="false" accessible="false" x="10" y="59" width="339" height="83" index="0">
                        <XCUIElementTypeOther type="XCUIElementTypeOther" enabled="true" visible="false" accessible="false" x="10" y="59" width="339" height="83" index="0"/>
                      </XCUIElementTypeOther>
                      <XCUIElementTypeOther type="XCUIElementTypeOther" enabled="true" visible="true" accessible="false" x="10" y="59" width="339" height="83" index="1">
                        <XCUIElementTypeOther type="XCUIElementTypeOther" enabled="true" visible="false" accessible="false" x="10" y="59" width="339" height="83" index="0"/>
                        <XCUIElementTypeOther type="XCUIElementTypeOther" enabled="true" visible="true" accessible="false" x="10" y="59" width="339" height="83" index="1">
                          <XCUIElementTypeOther type="XCUIElementTypeOther" enabled="true" visible="true" accessible="false" x="10" y="59" width="339" height="83" index="0">
                            <XCUIElementTypeStaticText type="XCUIElementTypeStaticText" value="교통량 정보를 찾으시나요?" name="교통량 정보를 찾으시나요?" label="교통량 정보를 찾으시나요?" enabled="true" visible="true" accessible="true" x="36" y="81" width="249" height="21" index="0"/>
                            <XCUIElementTypeButton type="XCUIElementTypeButton" name="닫기" label="닫기" enabled="true" visible="true" accessible="true" x="296" y="81" width="18" height="23" index="1"/>
                            <XCUIElementTypeStaticText type="XCUIElementTypeStaticText" value="탭하여 지도 선택" name="탭하여 지도 선택" label="탭하여 지도 선택" enabled="true" visible="true" accessible="true" x="36" y="101" width="249" height="19" index="2"/>
                          </XCUIElementTypeOther>
                        </XCUIElementTypeOther>
                      </XCUIElementTypeOther>
                    </XCUIElementTypeOther>
                  </XCUIElementTypeOther>
                </XCUIElementTypeOther>
                <XCUIElementTypeOther type="XCUIElementTypeOther" enabled="true" visible="true" accessible="false" x="339" y="69" width="44" height="90" index="1">
                  <XCUIElementTypeOther type="XCUIElementTypeOther" enabled="true" visible="true" accessible="false" x="339" y="69" width="44" height="90" index="0">
                    <XCUIElementTypeOther type="XCUIElementTypeOther" enabled="true" visible="true" accessible="false" x="339" y="69" width="44" height="90" index="0">
                      <XCUIElementTypeOther type="XCUIElementTypeOther" enabled="true" visible="false" accessible="false" x="339" y="69" width="44" height="90" index="0">
                        <XCUIElementTypeOther type="XCUIElementTypeOther" enabled="true" visible="false" accessible="false" x="339" y="69" width="44" height="90" index="0"/>
                      </XCUIElementTypeOther>
                      <XCUIElementTypeOther type="XCUIElementTypeOther" enabled="true" visible="true" accessible="false" x="339" y="69" width="44" height="90" index="1">
                        <XCUIElementTypeOther type="XCUIElementTypeOther" enabled="true" visible="false" accessible="false" x="339" y="69" width="44" height="90" index="0"/>
                        <XCUIElementTypeOther type="XCUIElementTypeOther" enabled="true" visible="true" accessible="false" x="339" y="69" width="44" height="90" index="1">
                          <XCUIElementTypeOther type="XCUIElementTypeOther" enabled="true" visible="true" accessible="false" x="339" y="69" width="44" height="90" index="0">
                            <XCUIElementTypeOther type="XCUIElementTypeOther" enabled="true" visible="true" accessible="false" x="339" y="69" width="44" height="90" index="0">
                              <XCUIElementTypeButton type="XCUIElementTypeButton" name="SettingsButton.Explore" label="지도 모드" enabled="true" visible="true" accessible="true" x="339" y="69" width="44" height="45" index="0"/>
                              <XCUIElementTypeOther type="XCUIElementTypeOther" enabled="true" visible="true" accessible="false" x="339" y="113" width="44" height="1" index="1">
                                <XCUIElementTypeOther type="XCUIElementTypeOther" enabled="true" visible="true" accessible="false" x="339" y="113" width="44" height="1" index="0"/>
                              </XCUIElementTypeOther>
                              <XCUIElementTypeButton type="XCUIElementTypeButton" value="끔" name="UserLocationButton" label="추적" enabled="true" visible="true" accessible="true" x="339" y="114" width="44" height="45" index="2"/>
                            </XCUIElementTypeOther>
                          </XCUIElementTypeOther>
                        </XCUIElementTypeOther>
                      </XCUIElementTypeOther>
                    </XCUIElementTypeOther>
                  </XCUIElementTypeOther>
                </XCUIElementTypeOther>
              </XCUIElementTypeOther>
              <XCUIElementTypeButton type="XCUIElementTypeButton" name="WeatherStackView" label="대체로 청명함, 2도, 대기질, 51, 보통" enabled="true" visible="true" accessible="true" x="323" y="415" width="60" height="44" index="2">
                <XCUIElementTypeOther type="XCUIElementTypeOther" name="WeatherStackBlurView" enabled="true" visible="true" accessible="false" x="323" y="415" width="60" height="44" index="0">
                  <XCUIElementTypeOther type="XCUIElementTypeOther" enabled="true" visible="false" accessible="false" x="323" y="415" width="60" height="44" index="0"/>
                  <XCUIElementTypeOther type="XCUIElementTypeOther" name="WeatherStackContent" enabled="true" visible="true" accessible="false" x="323" y="415" width="60" height="44" index="1">
                    <XCUIElementTypeOther type="XCUIElementTypeOther" name="ContentStackView" enabled="true" visible="true" accessible="false" x="327" y="420" width="52" height="34" index="0">
                      <XCUIElementTypeOther type="XCUIElementTypeOther" name="WeatherConditionsView" enabled="true" visible="true" accessible="false" x="327" y="420" width="52" height="22" index="0">
                        <XCUIElementTypeOther type="XCUIElementTypeOther" name="WeatherConditionsContent" enabled="true" visible="true" accessible="false" x="333" y="420" width="41" height="22" index="0">
                          <XCUIElementTypeImage type="XCUIElementTypeImage" name="WeatherConditionsImageView" label="밝기 높게" enabled="true" visible="true" accessible="false" x="333" y="420" width="22" height="22" index="0"/>
                          <XCUIElementTypeStaticText type="XCUIElementTypeStaticText" value="2°" name="WeatherConditionsTitleLabel" label="2°" enabled="true" visible="true" accessible="false" x="355" y="420" width="19" height="22" index="1"/>
                        </XCUIElementTypeOther>
                      </XCUIElementTypeOther>
                      <XCUIElementTypeOther type="XCUIElementTypeOther" name="AirQualityConditionsView" enabled="true" visible="true" accessible="false" x="327" y="441" width="52" height="13" index="1">
                        <XCUIElementTypeOther type="XCUIElementTypeOther" name="AirQualityConditionsContent" enabled="true" visible="true" accessible="false" x="327" y="441" width="52" height="13" index="0">
                          <XCUIElementTypeStaticText type="XCUIElementTypeStaticText" value="대기질 51" name="AirQualityConditionsTitleLabel" label="대기질 51" enabled="true" visible="true" accessible="false" x="327" y="441" width="41" height="13" index="0"/>
                          <XCUIElementTypeOther type="XCUIElementTypeOther" name="AirQualityConditionsCircleView" enabled="true" visible="true" accessible="false" x="372" y="444" width="7" height="8" index="1"/>
                        </XCUIElementTypeOther>
                      </XCUIElementTypeOther>
                    </XCUIElementTypeOther>
                  </XCUIElementTypeOther>
                </XCUIElementTypeOther>
              </XCUIElementTypeButton>
            </XCUIElementTypeOther>
            <XCUIElementTypeOther type="XCUIElementTypeOther" name="IOSChromeViewController&lt;0x105821200&gt;.ControlContainerViewController&lt;0x10581ca00&gt;" enabled="true" visible="true" accessible="false" x="0" y="0" width="393" height="852" index="3">
              <XCUIElementTypeOther type="XCUIElementTypeOther" name="ControlContainerViewController.OverlayView" enabled="true" visible="true" accessible="false" x="0" y="59" width="393" height="410" index="0"/>
            </XCUIElementTypeOther>
            <XCUIElementTypeOther type="XCUIElementTypeOther" name="ChromeViewController.Viewport" enabled="true" visible="true" accessible="false" x="0" y="59" width="339" height="759" index="4"/>
          </XCUIElementTypeOther>
        </XCUIElementTypeOther>
      </XCUIElementTypeOther>
      <XCUIElementTypeOther type="XCUIElementTypeOther" enabled="true" visible="true" accessible="false" x="0" y="0" width="393" height="852" index="1">
        <XCUIElementTypeOther type="XCUIElementTypeOther" enabled="true" visible="true" accessible="false" x="-393" y="-852" width="1179" height="2556" index="0"/>
        <XCUIElementTypeOther type="XCUIElementTypeOther" enabled="true" visible="true" accessible="false" x="0" y="468" width="393" height="384" index="1">
          <XCUIElementTypeButton type="XCUIElementTypeButton" value="절반 화면" name="Card grabber" label="카드 제어기" enabled="true" visible="true" accessible="true" x="158" y="463" width="77" height="26" index="0"/>
          <XCUIElementTypeOther type="XCUIElementTypeOther" enabled="true" visible="true" accessible="false" x="0" y="468" width="393" height="384" index="1">
            <XCUIElementTypeOther type="XCUIElementTypeOther" enabled="true" visible="true" accessible="false" x="0" y="468" width="393" height="384" index="0">
              <XCUIElementTypeOther type="XCUIElementTypeOther" enabled="true" visible="true" accessible="false" x="0" y="468" width="393" height="384" index="0">
                <XCUIElementTypeOther type="XCUIElementTypeOther" enabled="true" visible="true" accessible="false" x="0" y="468" width="393" height="71" index="0">
                  <XCUIElementTypeOther type="XCUIElementTypeOther" name="MapsSearchBar" enabled="true" visible="true" accessible="false" x="0" y="468" width="393" height="71" index="0">
                    <XCUIElementTypeImage type="XCUIElementTypeImage" enabled="true" visible="false" accessible="false" x="0" y="468" width="393" height="71" index="0"/>
                    <XCUIElementTypeOther type="XCUIElementTypeOther" enabled="true" visible="true" accessible="false" x="0" y="468" width="393" height="71" index="1">
                      <XCUIElementTypeSearchField type="XCUIElementTypeSearchField" name="MapsSearchTextField" label="지도 검색" enabled="true" visible="true" accessible="true" x="16" y="485" width="315" height="37" index="0">
                        <XCUIElementTypeButton type="XCUIElementTypeButton" name="Dictate" label="받아쓰기" enabled="true" visible="true" accessible="false" x="305" y="492" width="18" height="23" index="0"/>
                        <XCUIElementTypeImage type="XCUIElementTypeImage" name="magnifyingglass" label="검색" enabled="true" visible="true" accessible="false" x="22" y="494" width="21" height="19" index="1"/>
                        <XCUIElementTypeButton type="XCUIElementTypeButton" name="Dictate" label="받아쓰기" enabled="true" visible="true" accessible="false" x="305" y="492" width="18" height="23" index="2"/>
                      </XCUIElementTypeSearchField>
                    </XCUIElementTypeOther>
                  </XCUIElementTypeOther>
                  <XCUIElementTypeButton type="XCUIElementTypeButton" name="userProfileButton" label="프로필" enabled="true" visible="true" accessible="true" x="341" y="485" width="36" height="37" index="1"/>
                </XCUIElementTypeOther>
                <XCUIElementTypeOther type="XCUIElementTypeOther" enabled="true" visible="true" accessible="false" x="0" y="468" width="393" height="384" index="1">
                  <XCUIElementTypeOther type="XCUIElementTypeOther" enabled="true" visible="true" accessible="false" x="0" y="468" width="393" height="384" index="0"/>
                </XCUIElementTypeOther>
                <XCUIElementTypeOther type="XCUIElementTypeOther" enabled="true" visible="true" accessible="false" x="0" y="538" width="393" height="314" index="2">
                  <XCUIElementTypeOther type="XCUIElementTypeOther" name="HomeView" enabled="true" visible="true" accessible="false" x="0" y="538" width="393" height="314" index="0">
                    <XCUIElementTypeCollectionView type="XCUIElementTypeCollectionView" name="위치" label="위치" enabled="true" visible="true" accessible="false" x="0" y="538" width="393" height="314" index="0">
                      <XCUIElementTypeOther type="XCUIElementTypeOther" enabled="true" visible="true" accessible="false" x="-20" y="538" width="433" height="205" index="0"/>
                      <XCUIElementTypeOther type="XCUIElementTypeOther" name="HomeShortcutsSectionHeaderView" enabled="true" visible="true" accessible="false" x="20" y="538" width="353" height="30" index="1">
                        <XCUIElementTypeOther type="XCUIElementTypeOther" name="HomeShortcutsSection" enabled="true" visible="true" accessible="false" x="20" y="538" width="353" height="30" index="0">
                          <XCUIElementTypeOther type="XCUIElementTypeOther" name="HomeShortcutsTitle" label="보관함" enabled="true" visible="true" accessible="false" x="20" y="539" width="39" height="19" index="0">
                            <XCUIElementTypeOther type="XCUIElementTypeOther" enabled="true" visible="true" accessible="false" x="20" y="539" width="39" height="19" index="0">
                              <XCUIElementTypeStaticText type="XCUIElementTypeStaticText" value="보관함" name="보관함" label="보관함" enabled="true" visible="true" accessible="true" x="20" y="539" width="39" height="19" index="0"/>
                            </XCUIElementTypeOther>
                          </XCUIElementTypeOther>
                        </XCUIElementTypeOther>
                      </XCUIElementTypeOther>
                      <XCUIElementTypeCell type="XCUIElementTypeCell" enabled="true" visible="true" accessible="false" x="20" y="567" width="353" height="132" index="2">
                        <XCUIElementTypeOther type="XCUIElementTypeOther" enabled="true" visible="true" accessible="false" x="20" y="567" width="353" height="132" index="0">
                          <XCUIElementTypeCollectionView type="XCUIElementTypeCollectionView" name="ShortcutsRowTableViewCellCollectionView" enabled="true" visible="true" accessible="false" x="20" y="567" width="353" height="132" index="0">
                            <XCUIElementTypeOther type="XCUIElementTypeOther" enabled="true" visible="true" accessible="false" x="20" y="567" width="353" height="132" index="0">
                              <XCUIElementTypeOther type="XCUIElementTypeOther" enabled="true" visible="true" accessible="false" x="20" y="567" width="353" height="132" index="0"/>
                            </XCUIElementTypeOther>
                            <XCUIElementTypeCell type="XCUIElementTypeCell" value="추가" name="ShortcutsRowCell" label="집" enabled="true" visible="true" accessible="true" x="26" y="567" width="81" height="132" index="1">
                              <XCUIElementTypeOther type="XCUIElementTypeOther" enabled="true" visible="true" accessible="false" x="26" y="567" width="81" height="132" index="0">
                                <XCUIElementTypeOther type="XCUIElementTypeOther" enabled="true" visible="false" accessible="false" x="36" y="583" width="61" height="61" index="0">
                                  <XCUIElementTypeOther type="XCUIElementTypeOther" enabled="true" visible="false" accessible="false" x="36" y="583" width="61" height="61" index="0"/>
                                </XCUIElementTypeOther>
                                <XCUIElementTypeImage type="XCUIElementTypeImage" name="ShortcutImage" enabled="true" visible="true" accessible="false" x="36" y="583" width="61" height="61" index="1"/>
                                <XCUIElementTypeStaticText type="XCUIElementTypeStaticText" value="집" name="ShortcutTitle" label="집" enabled="true" visible="true" accessible="false" x="30" y="650" width="73" height="19" index="2"/>
                                <XCUIElementTypeStaticText type="XCUIElementTypeStaticText" value="추가" name="ShortcutSubtitle" label="추가" enabled="true" visible="true" accessible="false" x="30" y="668" width="73" height="17" index="3"/>
                              </XCUIElementTypeOther>
                            </XCUIElementTypeCell>
                            <XCUIElementTypeCell type="XCUIElementTypeCell" value="추가" name="ShortcutsRowCell" label="직장" enabled="true" visible="true" accessible="true" x="106" y="567" width="81" height="132" index="2">
                              <XCUIElementTypeOther type="XCUIElementTypeOther" enabled="true" visible="true" accessible="false" x="106" y="567" width="81" height="132" index="0">
                                <XCUIElementTypeOther type="XCUIElementTypeOther" enabled="true" visible="false" accessible="false" x="116" y="583" width="61" height="61" index="0">
                                  <XCUIElementTypeOther type="XCUIElementTypeOther" enabled="true" visible="false" accessible="false" x="116" y="583" width="61" height="61" index="0"/>
                                </XCUIElementTypeOther>
                                <XCUIElementTypeImage type="XCUIElementTypeImage" name="ShortcutImage" enabled="true" visible="true" accessible="false" x="116" y="583" width="61" height="61" index="1"/>
                                <XCUIElementTypeStaticText type="XCUIElementTypeStaticText" value="직장" name="ShortcutTitle" label="직장" enabled="true" visible="true" accessible="false" x="110" y="650" width="73" height="19" index="2"/>
                                <XCUIElementTypeStaticText type="XCUIElementTypeStaticText" value="추가" name="ShortcutSubtitle" label="추가" enabled="true" visible="true" accessible="false" x="110" y="668" width="73" height="17" index="3"/>
                              </XCUIElementTypeOther>
                            </XCUIElementTypeCell>
                            <XCUIElementTypeCell type="XCUIElementTypeCell" name="ShortcutsRowCell" label="추가" enabled="true" visible="true" accessible="true" x="186" y="567" width="81" height="132" index="3">
                              <XCUIElementTypeOther type="XCUIElementTypeOther" enabled="true" visible="true" accessible="false" x="186" y="567" width="81" height="132" index="0">
                                <XCUIElementTypeOther type="XCUIElementTypeOther" enabled="true" visible="true" accessible="false" x="197" y="583" width="60" height="61" index="0">
                                  <XCUIElementTypeOther type="XCUIElementTypeOther" enabled="true" visible="true" accessible="false" x="197" y="583" width="60" height="61" index="0"/>
                                </XCUIElementTypeOther>
                                <XCUIElementTypeImage type="XCUIElementTypeImage" name="ShortcutImage" label="추가" enabled="true" visible="true" accessible="false" x="197" y="586" width="60" height="56" index="1"/>
                                <XCUIElementTypeStaticText type="XCUIElementTypeStaticText" value="추가" name="ShortcutTitle" label="추가" enabled="true" visible="true" accessible="false" x="190" y="650" width="73" height="19" index="2"/>
                              </XCUIElementTypeOther>
                            </XCUIElementTypeCell>
                            <XCUIElementTypeOther type="XCUIElementTypeOther" value="0%" name="수직 스크롤 막대, 1페이지" label="수직 스크롤 막대, 1페이지" enabled="true" visible="true" accessible="false" x="340" y="567" width="30" height="132" index="4">
                              <XCUIElementTypeOther type="XCUIElementTypeOther" enabled="true" visible="false" accessible="false" x="367" y="528" width="3" height="37" index="0"/>
                            </XCUIElementTypeOther>
                            <XCUIElementTypeOther type="XCUIElementTypeOther" value="0%" name="수직 스크롤 막대, 1페이지" label="수직 스크롤 막대, 1페이지" enabled="true" visible="true" accessible="false" x="340" y="567" width="30" height="132" index="5">
                              <XCUIElementTypeOther type="XCUIElementTypeOther" enabled="true" visible="false" accessible="false" x="367" y="528" width="3" height="37" index="0"/>
                            </XCUIElementTypeOther>
                          </XCUIElementTypeCollectionView>
                        </XCUIElementTypeOther>
                      </XCUIElementTypeCell>
                      <XCUIElementTypeCell type="XCUIElementTypeCell" name="LibraryLinkCell" label="0개의 장소 • 0개의 가이드 • 0개의 경로" enabled="true" visible="true" accessible="true" x="20" y="698" width="353" height="45" index="3">
                        <XCUIElementTypeOther type="XCUIElementTypeOther" enabled="true" visible="true" accessible="false" x="20" y="698" width="353" height="45" index="0">
                          <XCUIElementTypeOther type="XCUIElementTypeOther" enabled="true" visible="true" accessible="false" x="20" y="698" width="353" height="45" index="0"/>
                        </XCUIElementTypeOther>
                        <XCUIElementTypeOther type="XCUIElementTypeOther" enabled="true" visible="true" accessible="false" x="20" y="698" width="319" height="45" index="1">
                          <XCUIElementTypeStaticText type="XCUIElementTypeStaticText" value="0개의 장소 • 0개의 가이드 • 0개의 경로" name="0개의 장소 • 0개의 가이드 • 0개의 경로" label="0개의 장소 • 0개의 가이드 • 0개의 경로" enabled="true" visible="true" accessible="false" x="40" y="710" width="268" height="21" index="0"/>
                        </XCUIElementTypeOther>
                        <XCUIElementTypeOther type="XCUIElementTypeOther" enabled="false" visible="true" accessible="false" x="339" y="713" width="14" height="15" index="2">
                          <XCUIElementTypeImage type="XCUIElementTypeImage" name="chevron.forward" label="앞으로" enabled="true" visible="true" accessible="false" x="340" y="713" width="11" height="15" index="0"/>
                        </XCUIElementTypeOther>
                      </XCUIElementTypeCell>
                      <XCUIElementTypeOther type="XCUIElementTypeOther" enabled="true" visible="true" accessible="false" x="40" y="698" width="333" height="1" index="4"/>
                      <XCUIElementTypeCell type="XCUIElementTypeCell" enabled="true" visible="true" accessible="false" x="0" y="742" width="393" height="176" index="5">
                        <XCUIElementTypeOther type="XCUIElementTypeOther" enabled="true" visible="true" accessible="false" x="0" y="742" width="393" height="176" index="0">
                          <XCUIElementTypeOther type="XCUIElementTypeOther" enabled="true" visible="true" accessible="false" x="0" y="742" width="393" height="176" index="0">
                            <XCUIElementTypeButton type="XCUIElementTypeButton" name="나의 위치 표시" label="나의 위치 표시" enabled="true" visible="true" accessible="true" x="16" y="762" width="361" height="49" index="0">
                              <XCUIElementTypeStaticText type="XCUIElementTypeStaticText" value="나의 위치 표시" name="나의 위치 표시" label="나의 위치 표시" enabled="true" visible="true" accessible="false" x="153" y="777" width="87" height="19" index="0"/>
                            </XCUIElementTypeButton>
                            <XCUIElementTypeButton type="XCUIElementTypeButton" name="문제 리포트" label="문제 리포트" enabled="true" visible="true" accessible="true" x="16" y="820" width="361" height="49" index="1">
                              <XCUIElementTypeStaticText type="XCUIElementTypeStaticText" value="문제 리포트" name="문제 리포트" label="문제 리포트" enabled="true" visible="true" accessible="false" x="162" y="835" width="69" height="19" index="0"/>
                            </XCUIElementTypeButton>
                            <XCUIElementTypeButton type="XCUIElementTypeButton" name="이용 약관" label="이용 약관" enabled="true" visible="false" accessible="true" x="16" y="884" width="48" height="14" index="2">
                              <XCUIElementTypeStaticText type="XCUIElementTypeStaticText" value="이용 약관" name="이용 약관" label="이용 약관" enabled="true" visible="false" accessible="false" x="16" y="884" width="42" height="14" index="0"/>
                            </XCUIElementTypeButton>
                          </XCUIElementTypeOther>
                        </XCUIElementTypeOther>
                      </XCUIElementTypeCell>
                      <XCUIElementTypeOther type="XCUIElementTypeOther" value="0%" name="수직 스크롤 막대, 2페이지" label="수직 스크롤 막대, 2페이지" enabled="true" visible="true" accessible="false" x="360" y="563" width="30" height="240" index="6">
                        <XCUIElementTypeOther type="XCUIElementTypeOther" enabled="true" visible="true" accessible="false" x="387" y="792" width="3" height="8" index="0"/>
                      </XCUIElementTypeOther>
                      <XCUIElementTypeOther type="XCUIElementTypeOther" value="0%" name="수평 스크롤 막대, 1페이지" label="수평 스크롤 막대, 1페이지" enabled="true" visible="true" accessible="false" x="49" y="819" width="295" height="30" index="7">
                        <XCUIElementTypeOther type="XCUIElementTypeOther" enabled="true" visible="true" accessible="false" x="333" y="846" width="8" height="3" index="0"/>
                      </XCUIElementTypeOther>
                      <XCUIElementTypeOther type="XCUIElementTypeOther" value="0%" name="수직 스크롤 막대, 2페이지" label="수직 스크롤 막대, 2페이지" enabled="true" visible="true" accessible="false" x="360" y="563" width="30" height="240" index="8">
                        <XCUIElementTypeOther type="XCUIElementTypeOther" enabled="true" visible="true" accessible="false" x="387" y="792" width="3" height="8" index="0"/>
                      </XCUIElementTypeOther>
                      <XCUIElementTypeOther type="XCUIElementTypeOther" value="0%" name="수평 스크롤 막대, 1페이지" label="수평 스크롤 막대, 1페이지" enabled="true" visible="true" accessible="false" x="49" y="819" width="295" height="30" index="9">
                        <XCUIElementTypeOther type="XCUIElementTypeOther" enabled="true" visible="true" accessible="false" x="333" y="846" width="8" height="3" index="0"/>
                      </XCUIElementTypeOther>
                    </XCUIElementTypeCollectionView>
                  </XCUIElementTypeOther>
                </XCUIElementTypeOther>
              </XCUIElementTypeOther>
            </XCUIElementTypeOther>
          </XCUIElementTypeOther>
        </XCUIElementTypeOther>
      </XCUIElementTypeOther>
    </XCUIElementTypeWindow>
  </XCUIElementTypeApplication>
</AppiumAUT>
